scpup/__init__.py
scpup/game.py
scpup/_internal/__init__.py
scpup/_internal/loader.py
scpup/_internal/services.py
scpup/bases/__init__.py
scpup/bases/group.py
scpup/bases/sprite.py
scpup/bases/view.py
scpup/common/__init__.py
scpup/common/ctrl.py
scpup/common/enums.py
scpup/common/player.py
scpup/common/position.py
scpup/common/text.py
scpup/common/timer.py
scpup/utils/__init__.py
scpup/utils/ui.py
scpup-0.13.29.dist-info/METADATA
scpup-0.13.29.dist-info/WHEEL
scpup-0.13.29.dist-info/licenses/LICENSE
scpup-0.13.29.dist-info/RECORD
