Metadata-Version: 2.1
Name: scpup
Version: 0.13.29
Summary: AramEau python packages
Project-URL: Homepage, https://github.com/Aram-Eau/eau-py
Project-URL: Download Page, https://scpup-game.web.app
Author-email: Ivan Aram Gonzalez Su <ivan.ags.95@gmail.com>
License-File: LICENSE
Classifier: License :: OSI Approved :: MIT License
Classifier: Operating System :: Microsoft :: Windows
Classifier: Programming Language :: Python :: 3
Requires-Python: >=3.9
Requires-Dist: pygame>=2.0.1
